setup.py
Trevor_L_distributions/Binomialdistribution.py
Trevor_L_distributions/Gaussiandistribution.py
Trevor_L_distributions/Generaldistribution.py
Trevor_L_distributions/__init__.py
Trevor_L_distributions.egg-info/PKG-INFO
Trevor_L_distributions.egg-info/SOURCES.txt
Trevor_L_distributions.egg-info/dependency_links.txt
Trevor_L_distributions.egg-info/not-zip-safe
Trevor_L_distributions.egg-info/top_level.txt