Metadata-Version: 1.0
Name: Trevor-L-distributions
Version: 0.1
Summary: Gaussian and Binomial distributions
Home-page: UNKNOWN
Author: Trevor LaViale
Author-email: UNKNOWN
License: UNKNOWN
Platform: UNKNOWN
